linuxvoice/__init__.py
linuxvoice/linuxvoice.py
linuxvoice-1.3.2.dist-info/LICENSE
linuxvoice-1.3.2.dist-info/METADATA
linuxvoice-1.3.2.dist-info/WHEEL
linuxvoice-1.3.2.dist-info/top_level.txt
linuxvoice-1.3.2.dist-info/RECORD
