Metadata-Version: 2.1
Name: linuxvoice
Version: 1.3.2
Summary: A small package for downloading LINUXVOICE issues
Home-page: https://github.com/ahiliation/DOLLECT
Author: Jeffrin Jose T
Author-email: jeffrin@rajagiritech.edu.in
License: UNKNOWN
Platform: UNKNOWN
Classifier: Programming Language :: Python :: 3
Classifier: License :: OSI Approved :: GNU General Public License v3 or later (GPLv3+)
Classifier: Operating System :: OS Independent
Requires-Python: >=3.6
